{"is_source_file": true, "format": "TypeScript", "description": "This file defines an environment configuration object exporting various URL endpoints and environment variables for frontend configuration.", "external_files": ["process.env"], "external_methods": [], "published": ["env"], "classes": [], "methods": [], "calls": ["process.env.NEXT_PUBLIC_API_BASE", "process.env.NEXT_PUBLIC_BACKEND_URL", "process.env.NEXT_PUBLIC_FRONTEND_URL", "process.env.NEXT_PUBLIC_WS_URL", "process.env.NEXT_PUBLIC_NODE_ENV"], "search-terms": ["env", "NEXT_PUBLIC_API_BASE", "NEXT_PUBLIC_BACKEND_URL", "NEXT_PUBLIC_FRONTEND_URL", "NEXT_PUBLIC_WS_URL", "NODE_ENV"], "state": 2, "file_id": 12, "knowledge_revision": 27, "git_revision": "", "ctags": [{"_type": "tag", "name": "env", "path": "/home/kavia/workspace/code-generation/real-time-chat-application-47794-47803/chat_frontend/src/lib/env.ts", "pattern": "/^export const env = {$/", "language": "TypeScript", "kind": "constant"}], "hash": "6e2ef587c4b826a186a118d32846dcc6", "format-version": 4, "code-base-name": "chat_frontend", "filename": "chat_frontend/src/lib/env.ts", "revision_history": [{"27": ""}]}